toolguard/__init__.py
toolguard/buildtime/__init__.py
toolguard/buildtime/buildtime.py
toolguard/buildtime/data_types.py
toolguard/buildtime/gen_py/__init__.py
toolguard/buildtime/gen_py/domain_from_funcs.py
toolguard/buildtime/gen_py/domain_from_openapi.py
toolguard/buildtime/gen_py/gen_toolguards.py
toolguard/buildtime/gen_py/mellea_simple.py
toolguard/buildtime/gen_py/naming_conv.py
toolguard/buildtime/gen_py/tool_dependencies.py
toolguard/buildtime/gen_py/tool_guard_generator.py
toolguard/buildtime/gen_py/prompts/__init__.py
toolguard/buildtime/gen_py/prompts/gen_tests.py
toolguard/buildtime/gen_py/prompts/improve_guard.py
toolguard/buildtime/gen_py/prompts/pseudo_code.py
toolguard/buildtime/gen_py/templates/__init__.py
toolguard/buildtime/gen_py/templates/oas_api.j2
toolguard/buildtime/gen_py/templates/oas_api_impl.j2
toolguard/buildtime/gen_py/templates/tool_guard.j2
toolguard/buildtime/gen_py/templates/tool_item_guard.j2
toolguard/buildtime/gen_spec/__init__.py
toolguard/buildtime/gen_spec/data_types.py
toolguard/buildtime/gen_spec/fn_to_toolinfo.py
toolguard/buildtime/gen_spec/oas_to_toolinfo.py
toolguard/buildtime/gen_spec/spec_generator.py
toolguard/buildtime/gen_spec/utils.py
toolguard/buildtime/gen_spec/prompts/add_examples.txt
toolguard/buildtime/gen_spec/prompts/add_policies.txt
toolguard/buildtime/gen_spec/prompts/add_references.txt
toolguard/buildtime/gen_spec/prompts/create_examples.txt
toolguard/buildtime/gen_spec/prompts/create_policy.txt
toolguard/buildtime/gen_spec/prompts/create_short_examples.txt
toolguard/buildtime/gen_spec/prompts/examples_reviewer.txt
toolguard/buildtime/gen_spec/prompts/fix_example.txt
toolguard/buildtime/gen_spec/prompts/functions.txt
toolguard/buildtime/gen_spec/prompts/merge.txt
toolguard/buildtime/gen_spec/prompts/merge_and_split.txt
toolguard/buildtime/gen_spec/prompts/merge_examples.txt
toolguard/buildtime/gen_spec/prompts/policy_reviewer.txt
toolguard/buildtime/gen_spec/prompts/split.txt
toolguard-0.2.7.dist-info/METADATA
toolguard-0.2.7.dist-info/WHEEL
toolguard-0.2.7.dist-info/licenses/LICENSE
toolguard-0.2.7.dist-info/RECORD
