Metadata-Version: 2.4
Name: toolguard
Version: 0.2.7
Summary: Policy adherence code generation for guarding AI agent tools
Author-email: Naama Zwerdling <naamaz@il.ibm.com>, David Boaz <davidbo@il.ibm.com>
License:                                  Apache License
License-File: LICENSE
Classifier: License :: OSI Approved :: Apache Software License
Classifier: Operating System :: OS Independent
Classifier: Programming Language :: Python :: 3
Requires-Python: <3.14,>=3.10
Requires-Dist: datamodel-code-generator>=0.52.2
Requires-Dist: fastmcp>=2.13.0
Requires-Dist: langchain-core>=0.3.72
Requires-Dist: litellm<2.0.0
Requires-Dist: loguru
Requires-Dist: markdown>=3.7
Requires-Dist: mellea>=0.3.0
Requires-Dist: pydantic>=2.11.0
Requires-Dist: pyright>=1.1.408
Requires-Dist: pytest-asyncio>=1.3.0
Requires-Dist: pytest-json-report>=1.5.0
Requires-Dist: pytest>=8.3.3
Requires-Dist: smolagents>=1.21.3
